lisaglitch/__init__.py
lisaglitch/gap/__init__.py
lisaglitch/gap/mask.py
lisaglitch/glitch/__init__.py
lisaglitch/glitch/base.py
lisaglitch/glitch/flow.py
lisaglitch/glitch/lpf.py
lisaglitch/glitch/lpfdistrib.py
lisaglitch/glitch/math.py
lisaglitch/glitch/nsflow.py
lisaglitch/glitch/random.py
lisaglitch/glitch/read.py
lisaglitch/glitch/resnet.py
lisaglitch-2.0.0.dist-info/METADATA
lisaglitch-2.0.0.dist-info/WHEEL
lisaglitch-2.0.0.dist-info/licenses/LICENSE
lisaglitch-2.0.0.dist-info/RECORD
