Metadata-Version: 2.4
Name: lisaglitch
Version: 2.0.0
Summary: Generate realistic glitches and data gaps for LISA gravitational wave detector simulations
License: BSD 3-Clause
License-File: LICENSE
Keywords: LISA,simulation
Author: Jean-Baptiste Bayle
Author-email: j2b.bayle@gmail.com
Maintainer: Jean-Baptiste Bayle
Maintainer-email: j2b.bayle@gmail.com
Requires-Python: >=3.10,<4
Classifier: Intended Audience :: Science/Research
Classifier: Topic :: Scientific/Engineering :: Astronomy
Classifier: Topic :: Scientific/Engineering :: Physics
Requires-Dist: h5py (>=3.12.1,<4.0.0)
Requires-Dist: lisaconstants (>=2.0.0,<3.0.0)
Requires-Dist: matplotlib (>=3.9.2,<4.0.0)
Requires-Dist: numpy (>=2.1.2,<3.0.0)
Requires-Dist: scipy (>=1.14.1,<2.0.0)
Requires-Dist: torch (>=2.5.0,<3.0.0)
Project-URL: Documentation, https://lisa-simulation.pages.in2p3.fr/glitch
Project-URL: Download, https://gitlab.in2p3.fr/lisa-simulation/glitch/-/releases
Project-URL: Repository, https://gitlab.in2p3.fr/lisa-simulation/glitch
Project-URL: Tracker, https://gitlab.in2p3.fr/lisa-simulation/glitch/-/issues
